MANIFEST.in
README.rst
setup.cfg
setup.py
collective/__init__.py
collective.quickupload.egg-info/PKG-INFO
collective.quickupload.egg-info/SOURCES.txt
collective.quickupload.egg-info/dependency_links.txt
collective.quickupload.egg-info/entry_points.txt
collective.quickupload.egg-info/namespace_packages.txt
collective.quickupload.egg-info/not-zip-safe
collective.quickupload.egg-info/requires.txt
collective.quickupload.egg-info/top_level.txt
collective/quickupload/__init__.py
collective/quickupload/archetypes.py
collective/quickupload/config.py
collective/quickupload/configure.zcml
collective/quickupload/dexterity.py
collective/quickupload/interfaces.py
collective/quickupload/minimal.zcml
collective/quickupload/testing.py
collective/quickupload/browser/__init__.py
collective/quickupload/browser/configure.zcml
collective/quickupload/browser/interfaces.py
collective/quickupload/browser/quick_upload.pt
collective/quickupload/browser/quick_upload.py
collective/quickupload/browser/quickupload_settings.py
collective/quickupload/browser/quickupload_viewlet.pt
collective/quickupload/browser/ticket.py
collective/quickupload/browser/uploadcapable.py
collective/quickupload/browser/utils.py
collective/quickupload/browser/viewlets.py
collective/quickupload/browser/static/cancel.png
collective/quickupload/browser/static/fileuploader.css
collective/quickupload/browser/static/fileuploader.js
collective/quickupload/browser/static/helpers.js
collective/quickupload/browser/static/jquery.uploadify.js
collective/quickupload/browser/static/loading.gif
collective/quickupload/browser/static/swfobject.js
collective/quickupload/browser/static/upload.png
collective/quickupload/browser/static/uploader.swf
collective/quickupload/browser/static/uploadify.css
collective/quickupload/locales/collective.quickupload-manual.pot
collective/quickupload/locales/collective.quickupload.pot
collective/quickupload/locales/plone-manual.pot
collective/quickupload/locales/plone.pot
collective/quickupload/locales/update.sh
collective/quickupload/locales/cs/LC_MESSAGES/collective.quickupload.po
collective/quickupload/locales/cs/LC_MESSAGES/plone.po
collective/quickupload/locales/de/LC_MESSAGES/collective.quickupload.po
collective/quickupload/locales/de/LC_MESSAGES/plone.po
collective/quickupload/locales/es/LC_MESSAGES/collective.quickupload.po
