Metadata-Version: 2.1
Name: collective.quickupload
Version: 1.11.1
Summary: Pure javascript files upload tool for Plone, with drag and drop, multi selection, and progress bar.
Home-page: http://plone.org/products/collective.quickupload
Author: jean-mat Grimaldi
Author-email: jeanmat.grimaldi@gmail.com
License: GPL
Keywords: Plone Multiple Files Upload
Platform: UNKNOWN
Classifier: Topic :: Desktop Environment :: File Managers
Classifier: Programming Language :: Python
Classifier: Programming Language :: Python :: 2.7
Classifier: Framework :: Plone :: 4.2
Classifier: Framework :: Plone :: 4.3
Classifier: Natural Language :: English
Classifier: Natural Language :: French
Classifier: Natural Language :: German
Classifier: Natural Language :: Spanish
Classifier: Natural Language :: Finnish
Classifier: Natural Language :: Italian
Classifier: Natural Language :: Norwegian
Classifier: Natural Language :: English
Classifier: Natural Language :: Portuguese (Brazilian)
Classifier: Natural Language :: Chinese (Simplified)
Classifier: Natural Language :: Chinese (Traditional)
Classifier: License :: OSI Approved :: GNU Affero General Public License v3
Provides-Extra: test
